{"Productos":[{"cantidadVendida":0,"cantidadTotal":300.0,"concentracion":"null","codigo":"98613","tipo":"JARABES","talla":"null","precioUnidad":130.5,"dosis":5.0,"laboratorio":"MK","nombre":"Propoleo","numeroPastillas":"null","miligramos":"null","marca":"null","mililitros":"null","cantidadDisponible":37},{"cantidadVendida":0,"cantidadTotal":"null","concentracion":"null","codigo":"3871581","tipo":"ORTOPEDICOS","talla":"M","precioUnidad":55.0,"laboratorio":"MuletasLab","nombre":"Muleta","numeroPastillas":"null","miligramos":"null","marca":"MuletasLab","mililitros":"null","cantidadDisponible":15},{"cantidadVendida":10,"cantidadTotal":"null","concentracion":"null","codigo":"26335","tipo":"INYECCIONES","talla":"null","precioUnidad":45.0,"laboratorio":"Phizer","nombre":"Vacuna-Covid19","numeroPastillas":"null","miligramos":"null","marca":"null","mililitros":1.0,"cantidadDisponible":70},{"cantidadVendida":0,"cantidadTotal":"null","concentracion":"null","codigo":"4196198","tipo":"PASTILLAS","talla":"null","precioUnidad":30.0,"laboratorio":"Dolex","nombre":"Dolex","numeroPastillas":15,"miligramos":30.0,"marca":"null","mililitros":"null","cantidadDisponible":180},{"cantidadVendida":0,"cantidadTotal":"null","concentracion":"null","codigo":"3823421","tipo":"ORTOPEDICOS","talla":"S","precioUnidad":25.0,"laboratorio":"Ortopedia S.A.S","nombre":"Inmovilizador Muñeca","numeroPastillas":"null","miligramos":"null","marca":"Ortopedia S.A.S","mililitros":"null","cantidadDisponible":80},{"cantidadVendida":5,"cantidadTotal":"null","concentracion":"null","codigo":"41534","tipo":"INYECCIONES","talla":"null","precioUnidad":65.5,"laboratorio":"Phizer","nombre":"Tetano","numeroPastillas":"null","miligramos":"null","marca":"null","mililitros":2.0,"cantidadDisponible":25},{"cantidadVendida":0,"cantidadTotal":"null","concentracion":"null","codigo":"2497629","tipo":"ORTOPEDICOS","talla":"L","precioUnidad":75.0,"laboratorio":"MuletasLab","nombre":"Muleta","numeroPastillas":"null","miligramos":"null","marca":"MuletasLab","mililitros":"null","cantidadDisponible":10},{"cantidadVendida":0,"cantidadTotal":"null","concentracion":0.3,"codigo":"423123634","tipo":"TOPICOS","talla":"null","precioUnidad":100.0,"laboratorio":"TQ","nombre":"Humectante facial","numeroPastillas":"null","miligramos":"null","marca":"null","mililitros":"null","cantidadDisponible":42},{"cantidadVendida":0,"cantidadTotal":"null","concentracion":0.3,"codigo":"4214764","tipo":"TOPICOS","talla":"null","precioUnidad":150.0,"laboratorio":"TQ","nombre":"Crema Quemaduras","numeroPastillas":"null","miligramos":"null","marca":"null","mililitros":"null","cantidadDisponible":30},{"cantidadVendida":0,"cantidadTotal":"null","concentracion":"null","codigo":"2307201","tipo":"PASTILLAS","talla":"null","precioUnidad":30.0,"laboratorio":"QT","nombre":"Acetaminofem","numeroPastillas":50,"miligramos":5.0,"marca":"null","mililitros":"null","cantidadDisponible":180},{"cantidadVendida":0,"cantidadTotal":200.0,"concentracion":"null","codigo":"66181","tipo":"JARABES","talla":"null","precioUnidad":84.0,"dosis":10.0,"laboratorio":"MK","nombre":"Avrilax","numeroPastillas":"null","miligramos":"null","marca":"null","mililitros":"null","cantidadDisponible":50},{"cantidadVendida":0,"cantidadTotal":"null","concentracion":0.3,"codigo":"42313434","tipo":"TOPICOS","talla":"null","precioUnidad":80.5,"laboratorio":"TQ","nombre":"C4","numeroPastillas":"null","miligramos":"null","marca":"null","mililitros":"null","cantidadDisponible":73},{"cantidadVendida":0,"cantidadTotal":100.0,"concentracion":"null","codigo":"12312","tipo":"JARABES","talla":"null","precioUnidad":54.3,"dosis":5.0,"laboratorio":"MK","nombre":"Bisolvon","numeroPastillas":"null","miligramos":"null","marca":"null","mililitros":"null","cantidadDisponible":13},{"cantidadVendida":3,"cantidadTotal":"null","concentracion":"null","codigo":"213422","tipo":"INYECCIONES","talla":"null","precioUnidad":85.5,"laboratorio":"Phizer","nombre":"Inyeccion3","numeroPastillas":"null","miligramos":"null","marca":"null","mililitros":0.5,"cantidadDisponible":30}]}