{"Pacientes":[{"cedula":1,"rh":null,"direccion":null,"telefono":null,"nombre":"p1","fechaN":"2021-11-02","edad":11,"username":"u1","contraseña":"c1"},{"cedula":123456,"rh":"o+","direccion":"dir12345","telefono":"12345","nombre":"s","fechaN":"1997-12-28","edad":55,"username":"u123","contraseña":"c123"},{"cedula":2,"rh":null,"direccion":null,"telefono":null,"nombre":"p2","fechaN":"2021-11-02","edad":11,"username":"u2","contraseña":"c2"},{"cedula":3,"rh":null,"direccion":null,"telefono":null,"nombre":"p3","fechaN":"2021-07-02","edad":11,"username":"u3","contraseña":"c3"},{"cedula":4,"rh":null,"direccion":null,"telefono":null,"nombre":"p4","fechaN":"2021-11-02","edad":11,"username":"u4","contraseña":"c4"},{"cedula":234567,"rh":null,"direccion":null,"telefono":null,"nombre":"paula martinez","fechaN":"2021-11-03","edad":20,"username":"paulam","contraseña":"1234"},{"cedula":213,"rh":"a","direccion":"as","telefono":"213","nombre":"sad","fechaN":"2020-12-27","edad":123,"username":"c5","contraseña":"c6"},{"cedula":123,"rh":"o+","direccion":"sdfgh","telefono":"1365","nombre":"s","fechaN":"0097-12-31","edad":55,"username":"u11","contraseña":"c11"},{"cedula":1136889294,"rh":"o+","direccion":"Direccion 1","telefono":"124124123","nombre":"Santiago Barbosa","fechaN":"1997-12-28","edad":23,"username":"s1","contraseña":"c1"},{"cedula":1231,"rh":"O","direccion":"cra13212-32","telefono":"12414","nombre":"asd","fechaN":"1997-12-28","edad":23,"username":"user1","contraseña":"c1"}]}